topsis_aryaman_102303622/__init__.py
topsis_aryaman_102303622/topsis.py
topsis_aryaman_102303622-1.0.2.dist-info/licenses/LICENSE
topsis_aryaman_102303622-1.0.2.dist-info/METADATA
topsis_aryaman_102303622-1.0.2.dist-info/WHEEL
topsis_aryaman_102303622-1.0.2.dist-info/entry_points.txt
topsis_aryaman_102303622-1.0.2.dist-info/top_level.txt
topsis_aryaman_102303622-1.0.2.dist-info/RECORD
